SqlSupport/__init__.py
SqlSupport/Reg/__init__.py
SqlSupport/Reg/sup.py
SqlSupport-1.0.0.dist-info/LICENSE
SqlSupport-1.0.0.dist-info/METADATA
SqlSupport-1.0.0.dist-info/WHEEL
SqlSupport-1.0.0.dist-info/top_level.txt
SqlSupport-1.0.0.dist-info/RECORD
